my_activation/__init__.py
my_activation/activation.py
lili_activacion_keras-0.1.0.dist-info/LICENSE
lili_activacion_keras-0.1.0.dist-info/METADATA
lili_activacion_keras-0.1.0.dist-info/WHEEL
lili_activacion_keras-0.1.0.dist-info/top_level.txt
lili_activacion_keras-0.1.0.dist-info/RECORD
