Metadata-Version: 2.1
Name: lili-activacion-keras
Version: 0.1.0
Summary: Una función de activación personalizada para Keras
Home-page: UNKNOWN
Author: Lili Chen
Author-email: lilichen577@gmail.com
License: UNKNOWN
Platform: UNKNOWN
Classifier: Development Status :: 3 - Alpha
Classifier: Intended Audience :: Developers
Classifier: Topic :: Software Development :: Libraries
Classifier: License :: OSI Approved :: MIT License
Classifier: Programming Language :: Python :: 3
Classifier: Programming Language :: Python :: 3.7
Classifier: Programming Language :: Python :: 3.8
Classifier: Programming Language :: Python :: 3.9
Requires-Python: >=3.6
License-File: LICENSE
Requires-Dist: tensorflow (>=2.0)
